invoiceai/__init__.py
invoiceai/client.py
invoiceai/exceptions.py
invoiceai/types.py
invoiceai-1.0.0.dist-info/METADATA
invoiceai-1.0.0.dist-info/WHEEL
invoiceai-1.0.0.dist-info/top_level.txt
invoiceai-1.0.0.dist-info/RECORD
